FuyaoDownloadMusic/__init__.py
FuyaoDownloadMusic/download.py
FuyaoDownloadMusic/kugou.py
FuyaoDownloadMusic/netease.py
FuyaoDownloadMusic/js/KugouEncrypt.js
FuyaoDownloadMusic/js/NeteaseEncrypt.js
FuyaoDownloadMusic/utils/execJsUtil.py
FuyaoDownloadMusic/utils/getJSPath.py
fuyaodownloadmusic-0.0.8.dist-info/licenses/LICENSE
fuyaodownloadmusic-0.0.8.dist-info/METADATA
fuyaodownloadmusic-0.0.8.dist-info/WHEEL
fuyaodownloadmusic-0.0.8.dist-info/top_level.txt
fuyaodownloadmusic-0.0.8.dist-info/RECORD
