Metadata-Version: 2.4
Name: FuyaoDownloadMusic
Version: 0.0.8
Summary: 一个用于从主流音乐平台下载音乐的第三方库
Author-email: fuyao-norway <1959415641@qq.com>, fuyao-ziqiu <1987239025@qq.com>, fuyaoteam <fuyaoteam@gmail.com>
License: MIT License
Project-URL: Repository, https://github.com/fuyao-lhw/FuyaoDownloadMusic
Classifier: Programming Language :: Python :: 3
Classifier: License :: OSI Approved :: MIT License
Requires-Python: >=3.8
License-File: LICENSE
Requires-Dist: requests>=2.32.5
Requires-Dist: PyExecJs>=1.5.1
Dynamic: license-file
